{
    "MilanesaDePollo": [
        {
            "Ingrediente": "Milanesa de pollo",
            "Cantidad": "120",
            "Calorias": 136
        },
        {
            "Ingrediente": "Aceite",
            "Cantidad": "1/2",
            "Calorias": 1320
        },
        {
            "Ingrediente": "Pan molido",
            "Cantidad": "1",
            "Calorias": 132
        },
        {
            "Ingrediente": "Cebolla",
            "Cantidad": "3/2",
            "Calorias": 12
        },
        {
            "Ingrediente": "Ajo",
            "Cantidad": "1/2",
            "Calorias": 5
        }
    ],
    "Procedencia": "Mexico"
}